{
  "description": "create / delete a queue in Rackspace Public Cloud", 
  "parameters": {
    "username": {
      "type": "Optional[String]", 
      "description": "Rackspace username, overrides I(credentials)."
    }, 
    "name": {
      "type": "Optional[String]", 
      "description": "Name to give the queue"
    }, 
    "region": {
      "type": "Optional[String]", 
      "description": "Region to create an instance in."
    }, 
    "state": {
      "type": "Optional[String]", 
      "description": "Indicate desired state of the resource"
    }, 
    "verify_ssl": {
      "type": "Optional[String]", 
      "description": "Whether or not to require SSL validation of API endpoints."
    }, 
    "env": {
      "type": "Optional[String]", 
      "description": "Environment as configured in I(~/.pyrax.cfg), see U(https://github.com/rackspace/pyrax/blob/master/docs/getting_started.md#pyrax-configuration)."
    }, 
    "credentials": {
      "type": "Optional[String]", 
      "description": "File to find the Rackspace credentials in. Ignored if I(api_key) and I(username) are provided."
    }, 
    "api_key": {
      "type": "Optional[String]", 
      "description": "Rackspace API key, overrides I(credentials)."
    }
  }
}